torchility/__init__.py
torchility/datamodule.py
torchility/hooks.py
torchility/losses.py
torchility/metrics.py
torchility/tasks.py
torchility/trainer.py
torchility/callbacks/__init__.py
torchility/callbacks/common.py
torchility/callbacks/interpreters.py
torchility/callbacks/performances.py
torchility/callbacks/progress.py
torchility/utils/__init__.py
torchility/utils/metric_utils.py
torchility/utils/model_io.py
torchility/utils/plots.py
torchility/utils/utils.py
torchility/utils/yaml_config.py
torchility-0.9.dist-info/LICENSE
torchility-0.9.dist-info/METADATA
torchility-0.9.dist-info/WHEEL
torchility-0.9.dist-info/top_level.txt
torchility-0.9.dist-info/RECORD
