Metadata-Version: 2.1
Name: torchility
Version: 0.9
Home-page: https://github.com/hitlic/torchility
Author: hitlic
Author-email: liuchen.lic@gmail.com
License: MIT
Classifier: Development Status :: 3 - Alpha
Classifier: Programming Language :: Python :: 3
Classifier: License :: OSI Approved :: MIT License
Classifier: Operating System :: OS Independent
Requires-Python: >=3.8
License-File: LICENSE
Requires-Dist: torch (>=2.0)
Requires-Dist: pytorch-lightning (==2.0)
Requires-Dist: torchmetrics (==0.11.4)
Requires-Dist: matplotlib (>=3.3)
Requires-Dist: pyyaml (>=5.4)
Requires-Dist: tensorboardX (==2.6)
